image_inspector/__init__.py
image_inspector/cli.py
image_inspector/image_inspector.py
image_inspector-0.3.0.dist-info/DESCRIPTION.rst
image_inspector-0.3.0.dist-info/METADATA
image_inspector-0.3.0.dist-info/RECORD
image_inspector-0.3.0.dist-info/WHEEL
image_inspector-0.3.0.dist-info/entry_points.txt
image_inspector-0.3.0.dist-info/metadata.json
image_inspector-0.3.0.dist-info/top_level.txt
