Metadata-Version: 2.0
Name: image-inspector
Version: 0.3.0
Summary: Simple utility to export exif data from tiff images to csv.
Home-page: https://github.com/TNRIS/image_inspector
Author: TNRIS
Author-email: david.hickman@twdb.texas.gov
License: MIT license
Keywords: TNRIS,tif,tiff,exif
Platform: UNKNOWN
Classifier: Development Status :: 2 - Pre-Alpha
Classifier: Intended Audience :: Developers
Classifier: License :: OSI Approved :: MIT License
Classifier: Natural Language :: English
Classifier: Programming Language :: Python :: 2
Classifier: Programming Language :: Python :: 2.6
Classifier: Programming Language :: Python :: 2.7
Classifier: Programming Language :: Python :: 3
Classifier: Programming Language :: Python :: 3.3
Classifier: Programming Language :: Python :: 3.4
Classifier: Programming Language :: Python :: 3.5
Requires-Dist: Click (>=6.0)
Requires-Dist: ExifRead (>=2.1.2)
